<?xml version="1.0" encoding="UTF-8"?><i><chatserver>chat.bilibili.com</chatserver><chatid>63816448</chatid><mission>0</mission><maxlimit>3000</maxlimit><state>0</state><real_name>0</real_name><source>k-v</source><d p="412.75700,1,25,16777215,1566693603,0,951261a2,20736339130974210">Odd有点不地道</d><d p="1396.86100,1,25,16777215,1571114541,0,ac609375,23054184190836738">我还以为可以听主题曲呢！</d><d p="328.73800,1,25,16777215,1580991528,0,8df565ae,28232570077446144">哼╭(╯^╰)╮</d><d p="1229.17100,1,25,16777215,1581772648,0,bc12742d,28642101802041344">行动点（AP）用完了？</d><d p="582.55800,1,25,41194,1582285488,0,1d3b0912,28910977643708420">夏之纳真会挑时间</d><d p="60.83000,1,25,16777215,1582771386,0,3474b10b,29165727880577027">一黑板化学你逗我呢？？？？？？？？</d><d p="829.98400,1,25,16777215,1582772551,0,3474b10b,29166338893152261">翻译好评</d><d p="95.26900,1,25,16777215,1582897211,0,a37824fd,29231696601153541">这明明讲的化学！！！</d><d p="336.14200,1,25,16777215,1583407412,0,d89bdb92,29499188760805379">A姐生气啦</d><d p="1186.22300,1,25,16777215,1584575020,0,53724ad7,30111351591927815">好评好评</d><d p="102.59700,1,25,16777215,1586781269,0,954b4e5,31268061398958083">太美的承诺因为太年轻hhh</d><d p="337.37900,1,25,16777215,1586781503,0,954b4e5,31268184457740359">哼，狗男人</d><d p="349.60100,1,25,16777215,1586781516,0,954b4e5,31268190861393927">你竟然不是最在意我的</d><d p="1187.61400,1,25,16777215,1586782354,0,954b4e5,31268630190620677">双杀？</d><d p="875.60500,1,25,16777215,1587375908,0,74f0e0a5,31579823600041987">神准头</d></i>