<?xml version="1.0" encoding="UTF-8"?><i><chatserver>chat.bilibili.com</chatserver><chatid>3995614</chatid><mission>0</mission><maxlimit>3000</maxlimit><state>0</state><real_name>0</real_name><source>k-v</source><d p="373.09700,1,25,16777215,1599141964,0,13d55585,37748625644191747">夏之纳</d><d p="119.81700,1,25,16777215,1598172438,0,b62b0d37,37240314938261511">O和W的關係什麼時候這麼好了wwwww</d><d p="1349.72200,1,25,16777215,1596254422,0,73644645,36234721998929923">jim还是牛批，正常人刚脱离控制早晕了</d><d p="1295.14100,1,25,16777215,1595874618,0,813aaed9,36035595368136707">制作组心塞塞，这都被发现了哈哈</d><d p="596.33800,1,25,16777215,1593676153,0,84c45389,34882966727426053">233333</d><d p="254.46300,1,25,16777215,1592328761,0,385bef52,34176545312473095">天才女友</d><d p="303.04200,1,25,16777215,1589367297,0,b72578fa,32623884894732295">小纸条塞口袋啊</d><d p="749.04900,1,25,16777215,1588962897,0,5620f625,32411863070277637">太喜感</d><d p="622.56800,1,25,16777215,1587452567,0,1f7b77a6,31620015113895939">hhhhhhh</d><d p="346.75700,1,25,16777215,1586506255,0,b86f55ad,31123874807545863">哈哈哈哈哈，说明以前已经折了很多了</d><d p="621.37200,1,25,16777215,1584849802,0,e8de7428,30255416538562567">hhhh</d><d p="225.88600,1,25,16777215,1584849406,0,e8de7428,30255209176367175">dj aelita on the beat</d><d p="158.72700,1,25,16777215,1583247499,0,bebce5ed,29415348189003847">秒打脸。。。</d><d p="357.81800,5,25,16777215,1582423883,0,3474b10b,28983536646619136">你们没发现吗，应该是odd经常这么拿试卷折纸鹤，jim可能才会像刚才那样说</d><d p="749.04700,1,25,16777215,1582348031,0,1666f25c,28943768180752386">忽然想看jim被虚拟化……能单抗圆格吗</d><d p="1240.52200,1,25,16777215,1582036859,0,45be1dfe,28780624535879680">XN每次都留下Uwww</d><d p="1105.04600,1,25,16777215,1582036272,0,45be1dfe,28780316740026368">车——————</d><d p="1045.27300,1,25,16777215,1582036160,0,45be1dfe,28780257957904384">yumi眼神可爱</d><d p="806.82800,1,25,16777215,1582035913,0,45be1dfe,28780128229654532">jim：木大木大</d><d p="621.93600,1,25,16777215,1578489216,0,6044636d,26920637914677248">2333333</d><d p="751.44600,1,25,16777215,1575185590,0,5536ee8c,25188586406019074">莫名的喜感23333</d><d p="940.43300,1,25,16777215,1572089170,0,a2d13e50,23565170638323712">odd小天使总垫后</d><d p="1339.35300,1,25,16777215,1570251718,0,a2348693,22601816261787652">水母就像游戏里无敌的al存在   它也同时没有任何攻击性</d><d p="1139.12700,5,25,16707842,1569844883,0,7ff1bd62,22388517451595776">圆球不是50%血吗？？</d><d p="505.34900,5,25,16707842,1569844231,0,7ff1bd62,22388175564439556">哈哈哈，如果我是DJ你还会爱我吗</d><d p="1123.41900,1,25,16777215,1569155317,0,59f7bef1,22026986265247746">力量不足</d><d p="1123.41900,1,25,16777215,1569155298,0,59f7bef1,22026976477839360">是为了加速吧</d><d p="216.63500,1,25,16777215,1564680658,0,1fd1bcd4,19680976596631556">我的WY</d><d p="805.50400,1,25,16777215,1561731219,0,4970434a,18134620737896450">XANA作弊，这怎么打</d><d p="652.79300,1,25,16777215,1561030864,0,1a2a1b87,17767433239527424">polish是指擦亮，一般指皮鞋</d><d p="1266.89800,1,25,16777215,1560174530,0,20fe4696,17318467646521344">剩多少，都得干掉水母呀</d><d p="1199.95400,1,25,16777215,1560174463,0,20fe4696,17318432540721152">我还以为逆虚拟了座驾</d><d p="1030.28900,1,25,16777215,1560174293,0,20fe4696,17318343592640516">这摩托帅</d><d p="954.99300,1,25,16777215,1560174218,0,20fe4696,17318304115851264">这一季的Y学了体操，哈哈</d><d p="831.66600,1,25,16777215,1560174095,0,20fe4696,17318239439159300">它们不敢让你死</d><d p="795.07700,1,25,16777215,1560174058,0,20fe4696,17318220283248640">越来越强</d><d p="782.67400,1,25,16777215,1560174046,0,20fe4696,17318213762678788">它们不敢打A，直接跑</d><d p="694.97800,1,25,16777215,1560173958,0,20fe4696,17318167771086852">越来越聪明了</d><d p="380.30600,1,25,16777215,1560173644,0,20fe4696,17318003206520832">随便就控制，好危险呀</d><d p="226.22600,1,25,16777215,1560173441,0,20fe4696,17317896660189186">不喜欢W。。。</d><d p="182.53300,1,25,16777215,1560173365,0,20fe4696,17317856669597696">老夫老妻的感觉</d><d p="58.92900,1,25,16777215,1560173219,0,20fe4696,17317780080033792">OP是哪对？？</d><d p="301.89000,1,25,16777215,1559904505,0,39e965f5,17176896585334786">就这点要两小时</d><d p="1161.33500,1,25,16777215,1559103141,0,935c8021,16756751146156036">量子态的啊</d><d p="1324.83800,1,25,16777215,1558972783,0,9fe7b85c,16688405922447362">我霸宋不服</d><d p="1164.30000,1,25,16777215,1556975262,0,9f3ce465,15641129982623744">剧情需要HHHHH</d><d p="806.75800,1,25,16777215,1555080090,0,29b8e0a7,14647513975357440">哈哈哈哈</d><d p="1168.71300,1,25,16777215,1553943699,0,2dc44c8b,14051717928714242">hhhh好可爱</d><d p="533.82100,1,25,16777215,1553943032,0,2dc44c8b,14051367829110788">哈哈哈哈哈字幕好可爱</d><d p="1286.08100,1,25,11890,1552899490,0,8def74f1,13504251601354754">哈，这集怎么那么多严格的大爷</d><d p="1212.84400,1,25,11890,1552899398,0,8def74f1,13504203398316036">不是，你们一群吐槽弱的有完没完</d><d p="795.15800,1,25,11890,1552898967,0,8def74f1,13503977165422594">厉害了</d><d p="616.85500,1,25,11890,1552898785,0,8def74f1,13503881813164036">哈哈哈</d><d p="366.72100,1,25,11890,1552898520,0,8def74f1,13503743087607812">哦，不</d><d p="220.09700,1,25,11890,1552898289,0,8def74f1,13503621587533824">居然还是音乐天才</d><d p="161.70800,1,25,11890,1552898222,0,8def74f1,13503586590261248">哈哈哈哈</d><d p="119.06900,1,25,16777215,1552478427,0,d5cc7d61,13283493350998020">我少看了一季？</d><d p="1150.45400,1,25,16777215,1551934749,0,d8750736,12998449075060740">因为剧情需要</d><d p="668.46700,5,25,16777215,1551283768,0,b41a4401,12657147686944772">真的好听</d><d p="1207.66800,1,25,16777215,1550739055,0,bb3686f4,12371561324478532">a妹你起个墙挡一下也好啊</d><d p="363.20000,1,25,16777215,1550738178,0,bb3686f4,12371101712121860">jim好可爱啊hhhhh</d><d p="290.07800,1,25,16777215,1550738096,0,bb3686f4,12371058690097156">一个情敌拆两对cp</d><d p="1305.14400,1,25,16777215,1550507296,0,a9b0b044,12250053005541378">剧情需要呗</d><d p="1287.30400,1,25,16777215,1550507272,0,a9b0b044,12250040472961026">水母打不死的吗</d><d p="872.48900,1,25,16777215,1550506777,0,a9b0b044,12249780702412802">上次也是这招</d><d p="728.97800,1,25,16777215,1550506604,0,a9b0b044,12249689853788162">被控制了当然没事</d><d p="328.27300,1,25,16777215,1550506141,0,a9b0b044,12249447397326914">两个学渣</d><d p="578.47400,1,25,16777215,1549890066,0,353b649e,11926446706524162">哈哈哈</d><d p="340.25400,1,25,16777215,1549889882,0,353b649e,11926350064517120">前方高能</d><d p="252.33000,1,25,16777215,1549851833,0,f8a01633,11906401483358210">A妹太学霸了没办法</d><d p="1261.22600,1,25,16777215,1549543548,0,4433309f,11744771069968386">人家都要偷家了你还在打主宰</d><d p="791.33200,1,25,16777215,1549533648,0,f9b3efda,11739580598321154">绝望.jpg</d><d p="661.08400,1,25,16777215,1548660757,0,722fc11d,11281934449115138">cool</d><d p="537.61600,1,25,16777215,1548660632,0,722fc11d,11281869102907394">kiwi不是平常都被放在抽屉里吗。。</d><d p="328.02800,1,25,16777215,1548660352,0,722fc11d,11281722234109952">哈哈哈哈哈</d><d p="1270.90800,5,25,52480,1548605309,0,4ed1e9ac,11252863707643906">发现Ulrich的脚也很好看啊</d><d p="904.41100,5,25,52480,1548604839,0,4ed1e9ac,11252617514582018">终于ODD脸上没有黑了</d><d p="784.56900,5,25,52480,1548604705,0,4ed1e9ac,11252547241115650">wtf？</d><d p="929.02400,1,25,16777215,1548599999,0,940acc29,11250079737839616">你也有伴了</d><d p="807.25300,1,25,16777215,1548599865,0,940acc29,11250009403031554">真的是大块头啊</d><d p="1298.96200,1,25,16776960,1547644452,0,7ce67d4,10749098244702212">居然有人吐槽U神真的服了</d><d p="433.72600,1,25,16776960,1547642346,0,7ce67d4,10747993764921346">奥利奥！</d><d p="1266.39100,1,25,16777215,1546285656,0,b713d301,10036697787531266">真的好帅好帅</d><d p="12.09600,1,25,16777215,1546068613,0,a0ed6a85,9922904473993216">感谢字幕组</d><d p="735.90500,1,25,16777215,1545129081,0,19d654b6,9430319465758720">这姿势……</d><d p="623.06200,1,25,16777215,1543743544,0,3a868e10,8703898791444480">Odd的脸撞到哪里了，哈哈哈</d><d p="1162.12800,1,25,16777215,1543073575,0,9ac9999b,8352642063925248">闪电侠?</d><d p="1306.56100,1,25,16777215,1542887886,0,3640dc,8255287372808192">思考不了，实际就是很多漏洞</d><d p="479.53700,1,25,16777215,1542556989,0,1afe7a64,8081802345316352">我信了哈哈哈哈</d><d p="1120.26600,1,25,15138834,1542333639,0,9b0365bd,7964702588534784">老是用翻跟斗应该是制作组要省事hhh</d><d p="596.51100,1,25,16777215,1542197194,0,a535c233,7893166321041408">带回校长不是差不多吗</d><d p="25.36000,1,25,16777215,1542127286,0,2e9fb8a3,7856514305884160">感谢字幕组</d><d p="13.48000,1,25,16777215,1542127247,0,2e9fb8a3,7856493715521538">感谢字幕组</d><d p="13.48000,1,25,16777215,1542127242,0,2e9fb8a3,7856491150704640">感谢字幕组</d><d p="12.60100,1,25,16777215,1542127236,0,2e9fb8a3,7856487762231296">感谢字幕组</d><d p="12.08000,1,25,16777215,1542127222,0,2e9fb8a3,7856480619331584">感谢字幕组</d><d p="712.17500,1,25,16777215,1541405751,0,d01b626f,7478221800996866">孩子们</d><d p="709.51500,1,25,16777215,1541405744,0,d01b626f,7478218188128256">那你们应该去工厂啊</d><d p="1225.69300,1,25,9599289,1541182022,0,2bc58793,7360923784183808">先砍水母啊</d><d p="946.21600,1,25,9599289,1541181736,0,2bc58793,7360773389025280">他们的交通工具我都超喜欢的</d><d p="411.76300,1,25,9599289,1541181191,0,2bc58793,7360487736475648">直男</d><d p="377.65200,1,25,16777215,1541181146,0,2bc58793,7360464180740096">Jimbo！！！</d><d p="355.20000,1,25,16777215,1541181112,0,2bc58793,7360446369103874">Jim好闷骚啊</d><d p="269.53400,1,25,16777215,1541181013,0,2bc58793,7360394680074240">直男啊</d><d p="1005.32900,1,25,16777215,1538165200,0,2c9ebc70,5779240246575108">滑板还是不同型号的？？a妹定制喵喵板</d><d p="827.22100,1,25,16777215,1536601876,0,ed30a2fd,4959608083841026">钵水母纲is on the way</d><d p="730.34600,1,25,16777215,1536601753,0,ed30a2fd,4959543651991556">hh看得我好想玩，虽然玩过跳不起来</d><d p="375.36000,1,25,16777215,1536601377,0,ed30a2fd,4959346404884480">xana挨个入侵</d><d p="1229.87700,1,25,16777215,1535653632,0,7204e7e0,4462455259398146">真不明白没了解清楚剧情有些人劲吐槽</d><d p="1247.06900,1,25,16777215,1535119231,0,40611d1e,4182275121479680">水母无敌</d><d p="137.21600,1,25,16777215,1534215988,0,ddc39877,3708715331485700">这集有印象</d><d p="512.10600,5,25,16777215,1533299832,0,40e039a6,3228386172862464">W：你表妹真棒！</d><d p="1244.07300,1,25,16777215,1530521291,0,746f7970,1771630215823364">有时间问这个还不如赶紧干掉水母来得快些</d><d p="730.27300,1,25,16777215,1530520749,0,746f7970,1771346135089156">我是网络监管局网警001，前面AVI的IP已经被锁定，请静坐家中等待审查！</d><d p="1208.00000,5,25,15138834,1530386964,0,38263913,1701203983990786"> 你们吐槽董美娃的有完没完</d><d p="603.76500,1,25,14811775,1529078359,0,8c1c484f,1015118060060672">玩嗨了</d><d p="549.12500,1,25,14811775,1529078297,0,8c1c484f,1015085569933312">迈着优雅的小步伐</d><d p="355.78500,1,25,14811775,1529078088,0,8c1c484f,1014976413696000">他看上了Odd的千纸鹤</d><d p="562.24100,1,25,16777215,1528715129,0,62453149,824681245442052">神走位！！！</d><d p="1296.28900,1,25,16777215,1528430171,0,31e403a3,675281242161154">淡定   还有好几季呢   不会出事的</d><d p="550.52600,1,25,16777215,1527242233,0,52f00a4e,52459576229890">2333333</d><d p="540.04600,1,25,16777215,1527242220,0,52f00a4e,52452520886274">23333333</d><d p="500.92600,1,25,16776960,1526224451,0,754e4d0e,4535372116">前面那位你真的很严格</d><d p="449.30700,1,25,16776960,1526224356,0,754e4d0e,4535367226">硬核23333333</d><d p="270.75800,1,25,16777215,1525604722,0,f64f759b,4516847411">直男哈哈哈</d><d p="1130.90100,1,25,16777215,1525441758,0,a6be8838,4510654108">喂喂喂</d><d p="74.96100,1,25,16777215,1524048957,0,ace290cd,4469569420">原来都要翘小拇指啊～</d><d p="333.17100,1,25,16777215,1523694037,0,9b24357a,4459795016">一个纸鹤折了两个小时=_=</d><d p="1400.55100,5,25,16777215,1523086193,0,b41a4401,4444085737">模范夫妇</d><d p="303.17100,1,25,16777215,1522987150,0,8cd351c,4440200463">这题目什么鬼啊</d><d p="58.42500,1,25,16777215,1522986793,0,8cd351c,4440182183">氧气的摩尔质量是32g/mol</d><d p="354.35800,1,25,16777215,1522827986,0,c24383d2,4434625751">一只纸鹤就折服了你吗23333</d><d p="1321.20300,5,25,16711680,1522733912,0,96b7b7d1,4432414795">看你们这群家伙着急真有意思</d><d p="1175.48200,5,25,16711680,1522733750,0,96b7b7d1,4432410627">上一集说要加快逆虚拟化，现在就倒霉了吧</d><d p="866.05100,5,25,16711680,1522733421,0,96b7b7d1,4432401783">jim：接受挑战</d><d p="63.81800,1,25,16711680,1522732583,0,96b7b7d1,4432376549">我是从头看到尾的姨妈红</d><d p="657.32300,1,25,16777215,1522568680,0,71b0be16,4428336454">厉害了调虎离山</d><d p="530.20500,1,25,16777215,1522568494,0,71b0be16,4428328800">好可怜哈哈哈哈哈</d><d p="285.23700,1,25,16777215,1522415665,0,63f12e3b,4423188123">GIGN？</d><d p="170.81600,1,25,16777215,1522415532,0,63f12e3b,4423181626">你把圆头对方头？还问我为什么插不进去？</d><d p="74.24800,1,25,16777215,1522381953,0,485cb1c,4421991274">准备倒掉（我猜的）</d><d p="979.32600,1,25,16777215,1520742022,0,518934c,4380099111">蛇皮走位</d><d p="1219.09700,1,25,14811775,1519036472,0,bc53e4,4318521586">圆格会把她逼回去得</d><d p="510.42100,1,25,16777215,1518534936,0,2a7dd10a,4296066445">突然尬舞</d><d p="292.79900,4,25,16777215,1518518729,0,2a7dd10a,4294963603">这检查真TM6</d><d p="900.96400,1,25,16777215,1518288595,0,52f00a4e,4285387650">这一来坐在电脑前的人就跟危险了</d><d p="1354.06100,1,25,16777215,1517812950,0,789cb249,4256892444">jim太可爱了</d><d p="458.94400,1,25,16777215,1517705683,0,baf747fb,4252488327">其實我覺得w人不錯</d><d p="1352.34400,1,25,16777215,1516848553,0,505bf5ab,4211402801">声控呢</d><d p="1335.02400,1,25,16777215,1516848536,0,505bf5ab,4211402260">可以假设XANA是好人</d><d p="1128.14900,1,25,16777215,1516848242,0,505bf5ab,4211393616">秒了？</d><d p="1100.19500,1,25,16777215,1516848214,0,505bf5ab,4211392776">XANA无CD无蓝条。。</d><d p="876.82900,1,25,16777215,1516847989,0,505bf5ab,4211386440">好随便</d><d p="752.16200,1,25,16777215,1516847859,0,505bf5ab,4211382774">好想笑</d><d p="699.38300,1,25,16777215,1516847807,0,505bf5ab,4211381307">机智的可怕</d><d p="551.52100,1,25,16777215,1516847659,0,505bf5ab,4211377264">2333</d><d p="532.63000,1,25,16777215,1516847640,0,505bf5ab,4211376759">这狗无敌了</d><d p="490.33600,1,25,16777215,1516847598,0,505bf5ab,4211375635">哇。好帅</d><d p="429.62400,1,25,16777215,1516847537,0,505bf5ab,4211374043">这么恐怖</d><d p="378.97300,1,25,16777215,1516847429,0,505bf5ab,4211371038">导演说了算</d><d p="364.31200,1,25,16777215,1516847407,0,505bf5ab,4211370393">又来</d><d p="312.28300,1,25,16777215,1516847354,0,505bf5ab,4211368998">我也不会啊</d><d p="220.16400,1,25,16777215,1516847263,0,505bf5ab,4211366458">是老婆都抢</d><d p="172.88300,1,25,16777215,1516847215,0,505bf5ab,4211365175">抢老婆啦</d><d p="148.37300,1,25,16707842,1516412593,0,7e9029e1,4194674734">小时候站W和Y的我233333</d><d p="52.91400,1,25,16777215,1516248633,0,a26d5d06,4189690963">20180118青软</d><d p="329.73100,5,25,16777215,1515517421,0,9b8c6bf9,4169821001">他們是一對的</d><d p="1148.24500,1,25,16777215,1514520066,0,8335b2b2,4126365950">从小的印象就是那个女孩子很脆。。紫色毒液那集也是</d><d p="480.30100,1,25,16777215,1513154480,0,8c33ba3e,4033030192">为什么绑起来而不是直接干掉</d><d p="1081.94400,1,25,16777215,1513082982,0,97c685c6,4031634598">咦飞车来的</d><d p="1225.45300,1,25,16777215,1512384264,0,e4110a9a,4013227663">这个时候问还有用吗。。。</d><d p="732.45800,1,25,16777215,1511260401,0,911d6648,3979641515">这姿势一.一</d><d p="1070.85800,1,25,16751052,1510863224,0,8d404983,3968845833">啊 帅</d><d p="500.52400,1,25,16777215,1506875787,0,6170b8e4,3851394622">尬舞...</d><d p="1358.05300,1,25,6684825,1504321363,0,bbc722f4,3779380291">因为回档会让XANA更强，前几集说过了</d><d p="1144.20800,1,25,6684825,1504321113,0,bbc722f4,3779368678">还以为U的车只够一个人。。。</d><d p="899.62900,5,25,6684825,1504320848,0,bbc722f4,3779356112">劳模ood上线</d><d p="475.15000,1,25,16777215,1503652118,0,f8e0b716,3747143886">我竟然真信了_(:з」∠)_</d><d p="854.11000,1,25,16777215,1503509725,0,87e88203,3740109450">夏之纳的是计算机的运算能力所以技能用的快啊</d><d p="911.10500,1,25,16777215,1503107990,0,4b611546,3717119987">不用担心，很快就会有人来陪Jerery了</d><d p="906.24100,1,25,16777215,1503107705,0,4b611546,3717104168">他们为什么认为Jerery能对付武力值无敌的Jim</d><d p="734.92100,1,25,16777215,1503107435,0,4b611546,3717090435">前面的，Xana无所不能……</d><d p="657.39500,1,25,16777215,1503107317,0,4b611546,3717084390">果然挑落单的下手</d><d p="446.49900,1,25,16777215,1503107088,0,4b611546,3717072199">不，是挑落单的那个</d><d p="150.09200,1,25,16777215,1503052128,0,7c80e28d,3714574375">炫酷！</d><d p="1208.19200,1,25,16777215,1502892904,0,b63f403f,3706262250">因为a是演员 </d><d p="1208.19200,1,25,16777215,1502892885,0,b63f403f,3706260586">因为a</d><d p="514.57800,1,25,14811775,1502854108,0,e0134bf6,3703425142">想起了你老婆真棒拿个表情包23333</d><d p="1294.40400,1,25,16777215,1501678240,0,fec7d8e1,3640612066">这个镜头用过吧，反过来又放了一次hh</d><d p="754.53000,1,25,16777215,1501677659,0,fec7d8e1,3640565448">jim讲得好有坏蛋的feel啊</d><d p="339.41600,1,25,16777215,1501677211,0,fec7d8e1,3640529982">ODD到底是学霸还是学渣啊？</d><d p="368.49900,1,25,16777215,1501391681,0,4e06e18c,3624776999">放開jimbo!</d><d p="1106.06200,1,25,16777215,1500819115,0,333cd1dd,3596093498">违规停车的后果</d><d p="1169.45400,1,25,16777215,1500794755,0,5c5364dc,3594438469">XANA帅爆</d><d p="367.95000,1,25,9487136,1500639495,0,b455aefb,3587140240">看到了吧，被控制不是因为不强壮</d><d p="153.82900,1,25,9487136,1500638176,0,b455aefb,3587052573">打头????</d><d p="1142.09200,1,25,15772458,1500453405,0,adbee61c,3577982410">地:MMP</d><d p="1107.02800,1,25,15772458,1500453354,0,adbee61c,3577979406">大肥车没了</d><d p="406.65600,1,25,16777215,1500023150,0,13cff55a,3558411376">如果我是dj你会爱我吗</d><d p="1133.24700,1,25,16777215,1499832749,0,9d2ebded,3549495839">每次a都等着被虐 干嘛不跑</d><d p="521.04400,1,25,16777215,1499440261,0,276344f5,3532596113">hhh</d><d p="484.96700,1,25,16777215,1498835497,0,5d77eab5,3507348257">卢西奥是你吗</d><d p="961.47000,1,25,16751103,1497265631,0,1a828344,3452684371">O的胸前是kiwi在拉尿，0，</d><d p="614.96800,1,25,16751103,1497262012,0,1a828344,3452627117">W:不是你叫我跳的吗？？？</d><d p="1029.03000,1,25,16777215,1497107513,0,42143e86,3447685708">Y的车子一直都很像老人代步机</d><d p="208.68400,1,25,16777215,1497107498,0,42143e86,3447636340">我站WA</d><d p="500.22200,1,25,16777215,1496758222,0,a93a7095,3436549185">这音乐跟A的粉红色好配啊哈哈哈哈</d><d p="551.86600,1,25,16777215,1496135136,0,5b37fb5f,3418677572">23333333</d><d p="35.74900,1,25,16777215,1496135119,0,5b37fb5f,3418628819">日常感谢字幕组*7</d><d p="244.65200,1,25,15138834,1495080726,0,44701c90,3370362143">站一秒WA</d><d p="907.50200,5,25,6830715,1494925551,0,cfd711c,3364155986">劳模Odd上线</d><d p="796.44200,5,25,15138834,1494925549,0,cfd711c,3364148872">jimbo你好2333</d><d p="520.92700,5,25,15772458,1494925543,0,cfd711c,3364131446">已经沦落到叫狗的地步了么23333</d><d p="483.51400,1,25,16777215,1493784759,0,321b799d,3305245526">不不不，你才是DJ</d><d p="1106.09000,1,25,16777215,1493715938,0,55dc1b95,3302073060">车：mmp</d><d p="745.40300,1,25,16777215,1493266321,0,7a4345c6,3275982886">转这一下子莫名戳笑点</d><d p="553.02200,1,25,16777215,1493262719,0,7a4345c6,3275974074">高冷基维</d><d p="81.78900,1,25,16777215,1492438258,0,707b5169,3238169644">只有光合作用</d><d p="906.88000,1,25,16777215,1492427229,0,911ff07c,3237210130">同，这样危险的就是jeremy了啊</d><d p="842.12100,1,25,16777215,1491818769,0,5a18f097,3208926208">不停下来就直接命中了</d><d p="63.86800,1,25,16777215,1491228648,0,42898a56,3175178398">17.4.3前来打脸</d><d p="873.12500,1,25,16777215,1490504460,0,25edebfa,3143084906">xana:我上次打过你一回你忘了?</d><d p="333.61400,1,25,16777215,1490461262,0,739b73b2,3141673580">是4小时。。。。</d><d p="13.30300,1,25,16707842,1490281888,0,a617bfa,3132624828">感谢字幕组（顺便增加弹幕</d><d p="1276.63000,1,25,38979,1490270884,0,6418f1fd,3131804498">大家看这就是典型沉迷输出无心推车的反面教材</d><d p="1027.44900,1,25,38979,1490270880,0,6418f1fd,3131786184">飞蚊预判的不错啊</d><d p="761.45000,1,25,38979,1490267275,0,6418f1fd,3131768646">a：喵喵喵？？？</d><d p="644.07400,1,25,38979,1490267272,0,6418f1fd,3131760308">哈哈哈哈哈哈哈哈什么鬼</d><d p="533.31200,1,25,38979,1490267271,0,6418f1fd,3131751670">mongrel是gre词汇哟</d><d p="494.57000,1,25,38979,1490267270,0,6418f1fd,3131747634">如果我是dj你会爱我吗</d><d p="369.32200,1,25,16777215,1490019016,0,743f405e,3123483704">教练暗恋odd？</d><d p="1213.05000,1,25,16777215,1489831606,0,ff67f2e7,3114498774">刚才螺旋梯被圆格打坏了，没载具哪都去不了</d><d p="1033.74000,1,25,16777215,1489406901,0,d87f8ff3,3098727830">Y：老公我来了</d><d p="1148.78000,1,25,16777215,1488978589,0,d6242a08,3081137844">第一剧情需要 第二你说不用技能就算了 跑是没用的 触手很长（45集</d><d p="1175.55000,1,25,16777215,1487304753,0,277574a3,3013181194">这次好礼貌，没打晕他</d><d p="1111.23000,1,25,16777215,1487304752,0,277574a3,3013176482">你说要是圆格打到钵水母纲了</d><d p="6.22000,1,25,9599289,1487196405,0,336c5ceb,3008920932">感谢字幕组！大家好我是土黄君～</d><d p="1329.31000,1,25,16777215,1486300160,0,3d20e2ed,2959683680">每次都急得要死2333</d><d p="7.00400,1,25,16777215,1485475716,0,e651ef7e,2906403074">感谢字幕组</d><d p="1132.18000,1,25,16777215,1485165960,0,e7bad40b,2888360352">圆格一击必杀？</d><d p="896.10200,1,25,16777215,1485162355,0,e7bad40b,2888341122">我也想问</d><d p="784.78600,1,25,16777215,1485162354,0,e7bad40b,2888330058">卧槽</d><d p="789.49900,1,25,16777215,1485162354,0,e7bad40b,2888332060">jim and jimbo，没毛病</d><d p="293.33200,1,25,16777215,1485162345,0,e7bad40b,2888289518">卧槽hhh</d><d p="175.60800,1,25,16777215,1485162340,0,e7bad40b,2888267740">暂时不用</d><d p="1276.81000,1,25,14811775,1484953678,0,da81ce31,2876445778">先救人那飞蚊不攻击啊 等打死了就没人救了啊</d><d p="874.56400,1,25,16777215,1484665906,0,9be133f5,2861155705">2333333</d><d p="841.47800,1,25,16777215,1484665906,0,9be133f5,2861153299">？？？为什么停下来看它发招啊？</d><d p="557.79200,1,25,16777215,1484665900,0,9be133f5,2861127291">23333333333333333</d><d p="254.83100,1,25,16777215,1484283686,0,546f97fe,2841717233">这个W就是专业来抢老婆的吧</d><d p="239.89800,1,25,16777215,1484283685,0,546f97fe,2841715407">又开始撩A</d><d p="61.56900,1,25,16777215,1484283682,0,546f97fe,2841704109">17年都没人看了</d><d p="40.84500,1,25,16777215,1484283681,0,546f97fe,2841702103">现在还有人啊</d><d p="3.96900,1,25,16777215,1484283680,0,546f97fe,2841699251">有人吗</d><d p="1076.15000,1,25,16777215,1484140155,0,ccfc02dd,2836739911">会爆胎吗</d><d p="1018.49000,1,25,8700107,1483437983,0,89ef0787,2810204029">应该弄个后视镜</d><d p="1070.38000,1,25,8700107,1483437983,0,89ef0787,2810207789">这一幕帅到我了</d><d p="756.35000,1,25,8700107,1483437980,0,89ef0787,2810194767">这是第三次来了…</d><d p="248.13900,1,25,16707842,1482149308,0,15235e0f,2763962551">種族天賦</d><d p="46.39800,1,25,51,1481731959,0,55d82b37,2749427077">非常感谢字幕组~</d><d p="47.28200,1,25,51,1481728300,0,55d82b37,2749276863">第二季好多蓝，蓝字君改为超蓝君吧=。=登陆~</d><d p="277.32800,1,25,16777215,1481407586,0,3d24a5b3,2738197785">前面一个情敌两个用的别跑23333</d><d p="1135.72000,1,25,16777215,1480644600,0,fcd38d0,2710949327">一直想吐槽，为什么你遇到水母不跑不挣扎。。</d><d p="1018.13000,1,25,16777215,1480252171,0,633c285b,2700334143">是的你关了</d><d p="989.60800,1,25,16777215,1479960755,0,4953a7ca,2689083415">空中停顿</d><d p="1301.66000,1,25,16777215,1479895613,0,4953a7ca,2687465007">又这样撞墙</d><d p="1283.80000,1,25,16777215,1479895612,0,4953a7ca,2687464107">当扇子用？</d><d p="1195.43000,1,25,16777215,1479895610,0,4953a7ca,2687458559">又这样 yanbuyana</d><d p="1158.04000,1,25,16777215,1479895610,0,4953a7ca,2687456365">尼玛</d><d p="1124.03000,1,25,16777215,1479895609,0,4953a7ca,2687453593">好爆炸的呐喊</d><d p="1047.45900,1,25,16777215,1479895607,0,4953a7ca,2687449805">这何必</d><d p="968.09600,1,25,16777215,1479895606,0,4953a7ca,2687446259">甩屌射击</d><d p="994.19700,1,25,16777215,1479895606,0,4953a7ca,2687447481">空中停顿？</d><d p="946.92200,1,25,16777215,1479895605,0,4953a7ca,2687445273">肯定会给吸一会我觉得</d><d p="880.22400,1,25,16777215,1479895604,0,4953a7ca,2687442237">电脑控制还能打晕？</d><d p="797.56100,1,25,16777215,1479895603,0,4953a7ca,2687438417">哇擦  。。</d><d p="769.19400,1,25,16777215,1479895603,0,4953a7ca,2687437153">蹲了这么久啊</d><d p="749.44200,1,25,16777215,1479895602,0,4953a7ca,2687435397">玩得一脚好滑板</d><d p="749.94000,1,25,16777215,1479895602,0,4953a7ca,2687436279"> 我喜欢队友JIm</d><d p="695.16200,1,25,16777215,1479895601,0,4953a7ca,2687432519">这集的题材有点熟悉</d><d p="701.66600,1,25,16777215,1479895601,0,4953a7ca,2687433277">愤怒的小鸟</d><d p="724.10500,1,25,16777215,1479895601,0,4953a7ca,2687434295">哇</d><d p="655.75700,1,25,16777215,1479895599,0,4953a7ca,2687429359">怪不得不杀  这XNNA太踏马机智了吧</d><d p="563.92900,1,25,16777215,1479895598,0,4953a7ca,2687424653">哈哈</d><d p="602.59700,1,25,16777215,1479895598,0,4953a7ca,2687426305">校长也好过没人</d><d p="582.85800,1,25,16777215,1479895598,0,4953a7ca,2687425437">中国初中有这样多帅</d><d p="530.59600,1,25,16777215,1479895597,0,4953a7ca,2687423277">好狗</d><d p="548.86400,1,25,16777215,1479895597,0,4953a7ca,2687424095">啊</d><d p="486.05900,1,25,16777215,1479895596,0,4953a7ca,2687421271">shuai </d><d p="979.13800,1,25,16777215,1479024261,0,d2cff02a,2658432771">走踏马的蛇皮位。。。</d><d p="986.49100,1,25,16777215,1478322064,0,11b7d8a,2633196251">odd完美走a，技能衔接流畅，可惜预判失误</d><d p="420.53800,1,25,16777215,1476547928,0,74a8b2b1,2557768469">额，Jim怎么突然到任杰后面了？</d><d p="1355.52000,1,25,6830715,1473250098,0,20adf75c,2383305691">return to the past now</d><d p="1137.75000,1,25,6830715,1473250094,0,20adf75c,2383293845">又是这个动作</d><d p="1015.12000,1,25,6830715,1473250092,0,20adf75c,2383287437">没没没没没没没没</d><d p="1356.54000,1,25,41194,1473167343,0,e8e6bbe3,2380933693">知道XANA会变强还敢时间倒转？</d><d p="1324.63000,1,25,41194,1473167342,0,e8e6bbe3,2380930481">不要在意那些袭击</d><d p="1177.00000,1,25,41194,1473163739,0,e8e6bbe3,2380922407">所以Jeremy是被连椅子一起扔开了？</d><d p="1012.31000,1,25,41194,1473163736,0,e8e6bbe3,2380912649">没没没</d><d p="809.55700,1,25,41194,1473163733,0,e8e6bbe3,2380901999">Odd上回被揍过一回……</d><d p="650.24000,1,25,41194,1473163729,0,e8e6bbe3,2380891785">修拖鞋hhhhh</d><d p="557.05600,1,25,41194,1473163728,0,e8e6bbe3,2380886157">233333</d><d p="370.26100,1,25,41194,1473163724,0,e8e6bbe3,2380876199">Yeah!Jim again</d><d p="59.56200,1,25,41194,1473163719,0,e8e6bbe3,2380859699">这儿天蓝</d><d p="6.22900,1,25,41194,1473163718,0,e8e6bbe3,2380856339">第一季有个夺命狂笑……</d><d p="444.75900,1,25,14811775,1472562545,0,8244b376,2355936147">欧漏</d><d p="1019.90000,5,25,16777215,1472432993,0,9718a953,2347723967">是我关的</d><d p="468.13800,5,25,16777215,1472432984,0,9718a953,2347692493">爸爸已经放弃你了</d><d p="1245.13000,1,25,16777215,1472130589,0,2e2ada64,2328026421">心疼J的声优，明明这么爽，但是要发男声</d><d p="1159.63000,1,25,16777215,1472130587,0,2e2ada64,2328014079">JIM</d><d p="1159.63000,1,25,16777215,1472130587,0,2e2ada64,2328015337">JIMBO 为什么你还是这么熟练</d><d p="912.52300,1,25,16777215,1472130582,0,2e2ada64,2327987927">所以说，JJ是官配，你们不要闹</d><d p="746.46400,1,25,16777215,1472130579,0,2e2ada64,2327970225">JIM，为什么你这么熟练</d><d p="720.04100,1,25,16777215,1472130578,0,2e2ada64,2327966331">大叔拐带萝莉到工厂.avi</d><d p="645.70100,1,25,16777215,1472130577,0,2e2ada64,2327957395">一脸懵逼的Sissi</d><d p="597.67400,1,25,16777215,1472130576,0,2e2ada64,2327951241">自绑M男</d><d p="1068.90000,5,25,16777215,1472115951,0,b74417d4,2326790319">没时间解释了！快上车！</d><d p="566.90400,1,25,16777215,1472115940,0,b74417d4,2326739361">群魔乱舞</d><d p="504.48800,1,25,16777215,1472115939,0,b74417d4,2326733865">=-=</d><d p="729.51400,1,25,16777215,1471867727,0,797e515b,2311387851">人家可是XANA</d><d p="1330.48000,5,25,3407769,1471666363,0,c6af2fae,2297784155">苹果绿君表示BS强行逻辑→_→</d><d p="788.64900,5,25,3407769,1471666354,0,c6af2fae,2297735157">纳尼QAQ</d><d p="812.84800,5,25,3407769,1471666354,0,c6af2fae,2297737307">象转之术……</d><d p="644.01500,5,25,3407769,1471666352,0,c6af2fae,2297722669">Nice</d><d p="561.39700,5,25,3407769,1471666350,0,c6af2fae,2297715589">心疼KJ党</d><d p="477.51300,5,25,3407769,1471666349,0,c6af2fae,2297708537">hhhhhhhhh</d><d p="78.51100,5,25,16777215,1471666342,0,c6af2fae,2297675217">Snack 23333</d><d p="1112.28000,5,25,255,1471582881,0,876bb221,2292187907">A估计是给吓得不轻，然后脑容量就不够用了</d><d p="766.40700,5,25,255,1471582870,0,876bb221,2292119477">好厉害……X……</d><d p="665.23500,5,25,255,1471582869,0,876bb221,2292108823">你们怎么可以把A一个人留下？！</d><d p="313.82000,5,25,255,1471582863,0,876bb221,2292072357">坐的这么近……？</d><d p="288.01600,5,25,16777215,1471582862,0,876bb221,2292069613">宅男的苦恼╮(╯▽╰)╭</d><d p="1073.98000,1,25,16777215,1471546988,0,10bc9d37,2290515441">萌</d><d p="619.77600,1,25,16777215,1471546980,0,10bc9d37,2290503813">23333333333</d><d p="568.89600,1,25,16777215,1471543379,0,10bc9d37,2290502327">yumi：？？？</d><d p="474.95600,1,25,16777215,1471543377,0,10bc9d37,2290499743">2333333333</d><d p="345.33600,1,25,16777215,1471543375,0,10bc9d37,2290496191">233333333</d><d p="731.60900,1,25,16777215,1469865883,0,6c2e7731,2174101053">暂停学姿势</d><d p="1126.03000,1,25,15138834,1469707736,0,ac5f3245,2163610351">那么容易就被打败了</d><d p="916.38800,1,25,15138834,1469707732,0,ac5f3245,2163585997">J：别管我保护老婆要紧。。。</d><d p="783.62800,1,25,15138834,1469707728,0,ac5f3245,2163564011">还回分身呀</d><d p="548.32800,1,25,15138834,1469707723,0,ac5f3245,2163530613">哈哈哈哈哈哈</d><d p="317.72000,1,25,15138834,1469707715,0,ac5f3245,2163480367">学霸厉害</d><d p="275.03900,1,25,15138834,1469707713,0,ac5f3245,2163473161">威廉每次都会引起cp吵架。。。。。。</d><d p="184.07600,1,25,15138834,1469707710,0,ac5f3245,2163451045">老婆也厉害</d><d p="57.87900,1,25,15138834,1469707706,0,ac5f3245,2163425581">我是来自第一季的樱桃红</d><d p="14.15400,1,25,16777215,1469679140,0,bbd0e20b,2160734299">日常感谢字幕组</d><d p="1248.55000,1,25,16777215,1469430207,0,fa9047ce,2144414593">玩得很h嘛</d><d p="1163.57000,1,25,16777215,1469430205,0,fa9047ce,2144404579">。。这翻译</d><d p="618.27000,1,25,16777215,1469430195,0,fa9047ce,2144351101">哈哈。。。</d><d p="473.41300,1,25,16777215,1469430190,0,fa9047ce,2144328693">哈哈。。。</d><d p="268.00900,1,25,16777215,1468285777,0,3d7c7e2e,2073069155">爱因斯坦夫妇的日常闹架233</d><d p="1268.00000,1,25,6830715,1467961388,0,c26ad505,2054214537">疾跑，持续七秒，冷却一分钟</d><d p="816.21500,5,25,6830715,1467957779,0,c26ad505,2054176957">假设我目前很好</d><d p="746.64600,1,25,6830715,1467957776,0,c26ad505,2054166751">XANA男神我耐你好帅</d><d p="356.52300,1,25,6830715,1467957768,0,c26ad505,2054132441">收藏什么鬼</d><d p="221.95500,1,25,6830715,1467957765,0,c26ad505,2054117233">天赋技能</d><d p="576.39300,1,25,16777215,1467817910,0,291dd81f,2047313777">奇怪的舞步</d><d p="503.33300,1,25,16777215,1467817905,0,291dd81f,2047297205">分不出，但是挺好的</d><d p="1298.78000,1,25,16777215,1467720498,0,c96741b7,2041304417">动作要帅！！</d><d p="785.01000,5,25,16777215,1467018342,0,e636ec5e,2005015253">我去</d><d p="603.19700,5,25,16777215,1467018339,0,e636ec5e,2005004493">我劝你先日一下狗</d><d p="321.44400,5,25,16777215,1467018335,0,e636ec5e,2004987811">懵B！！！！！！！！！！</d><d p="313.65700,1,25,16777215,1467018334,0,e636ec5e,2004986105">ood懵B！！！！！！！！！！！</d><d p="305.47200,1,25,16777215,1466903357,0,38036010,1999191895">有时光倒流吗</d><d p="991.96000,1,25,16707842,1466741533,0,8a0c00c,1991302435">头好痛的样子</d><d p="54.50000,1,25,16707842,1466737916,0,8a0c00c,1991251281">檬黄报到</d><d p="1150.84000,1,25,41194,1466518216,0,fa3c49b7,1983314467">为什么不造个墙</d><d p="1307.28000,1,25,15138834,1466319800,0,7c8d84b1,1974864397">妈的不知道怎么想的，水母暂时没有攻击性，飞蚊把U打回去了救个毛A啊？</d><d p="377.58400,1,25,16777215,1465966917,0,48afa299,1960805117">您的好友 圆格已上线</d><d p="974.96700,1,25,16777215,1465553165,0,e6a5520a,1944344051">2333 螺旋走位的你别跑</d><d p="1031.92000,1,25,16777215,1465182699,0,bc7c5a1c,1928634825">yumi心疼老公</d><d p="205.33800,1,25,16777215,1464930060,0,b00c97e6,1918428119">你是來负责抢老婆的吗william </d><d p="75.06700,1,25,16777215,1464927178,0,b00c97e6,1918420959">ODD只会吃23</d><d p="28.97100,1,25,16777215,1464927177,0,b00c97e6,1918417659">ODD男神</d><d p="608.28200,1,25,16777215,1464869300,0,5a9cd933,1916814457">Electric  pop</d><d p="1338.52000,1,25,16777215,1464102685,0,6d537820,1887244991">每次类似这种捉急 (﹁"﹁) 情节，我都会安慰自己这是剧情需要→_→</d><d p="274.02700,1,25,16777215,1463847168,0,a9355fe4,1871660707">港真当年看到这一集的时候居然萌发了WA也不错的想法【捂脸】</d><d p="537.40800,1,25,16777215,1463656076,0,921bdf21,1862658047">懂開門</d><d p="430.82600,1,25,16777215,1463656075,0,921bdf21,1862652407">鎖門啊啊啊</d><d p="303.68000,1,25,16777215,1463656071,0,921bdf21,1862641339">為什麼我看不懂</d><d p="298.04800,1,25,16777215,1463656070,0,921bdf21,1862639483">一支筆怎考...</d><d p="716.16500,1,25,16777215,1463580623,0,e1f73659,1860594345">killer music</d><d p="637.63100,1,25,16777215,1463580622,0,e1f73659,1860589969">2333333333</d><d p="1340.18000,1,25,16777215,1463558697,0,9766ea88,1859719511">大Boss</d><d p="1148.87000,1,25,16777215,1463558695,0,9766ea88,1859716889">a妹啊</d><d p="1057.84000,1,25,16777215,1463558694,0,9766ea88,1859714057">a妹在等你啊</d><d p="1023.24000,1,25,16777215,1463511831,0,623c8b13,1858866723">U虚拟化是真帅</d><d p="140.73900,1,25,16777215,1463511816,0,623c8b13,1858860857">我想看小威哼哼</d><d p="58.30000,1,25,14811775,1463335368,0,7fcfd9a9,1854125517">我又捨不得跳op了</d><d p="898.59200,1,25,16777215,1463321441,0,a5daeec1,1853586561">。。。這樣留下J真好嗎？</d><d p="1312.53000,1,25,16777215,1463148656,0,5a0235e5,1845575317">走快點 少女</d><d p="1282.49000,1,25,16777215,1463148655,0,5a0235e5,1845573157">跟老婆一樣喜歡跳來跳去再斬</d><d p="288.56700,1,25,16777215,1463148640,0,5a0235e5,1845508391">今天真的祼考了....</d><d p="69.06000,1,25,16777215,1463148637,0,5a0235e5,1845492585">同伴你好</d><d p="984.86100,1,25,16777215,1463072480,0,4803773e,1842987169">猴子一樣的貓</d><d p="94.33500,1,25,16777215,1463022671,0,9bebc938,1840874217">前面不要再劇透行不？</d><d p="1313.93000,1,25,16777215,1462201919,0,b2060abe,1814821147">你们这样都能撕逼望天ing。。。 </d><d p="1350.48000,1,25,16777215,1461744249,0,25827677,1795606461">好几集没回档了吧</d><d p="1288.58000,1,25,16777215,1461744248,0,25827677,1795604349">剧情需要</d><d p="550.28500,1,25,16777215,1461416941,0,c3762a11,1784950055">kiwi：叫你刚才骂我</d><d p="1308.76000,1,25,16777215,1460736747,0,329b925d,1762217285">现在想想我的童年也有点悲催呢(摊手</d><d p="1272.63000,1,25,16777215,1460736746,0,329b925d,1762215783">直接砍啊……</d><d p="270.63100,1,25,16777215,1460128272,0,a7afc02c,1742897301">夫妻吵架。。。</d><d p="179.44700,1,25,16777215,1460128270,0,a7afc02c,1742889697">J:老婆不陪我了，不高兴。</d><d p="9.47300,1,25,16777215,1460128267,0,a7afc02c,1742875025">字幕组辛苦了╭(╯ε╰)╮</d><d p="889.69900,1,25,16777215,1460019947,0,d360bb68,1739063025">所以他们就把Jim留给J了吗。。</d><d p="645.11900,1,25,16750848,1459836122,0,cda48583,1734423121">polish flipflop 666666</d><d p="557.69800,1,25,16750848,1459836120,0,cda48583,1734420305">Odd躺枪</d><d p="219.85400,1,25,16750848,1459832515,0,cda48583,1734410763">Aelita的粉色感觉和电音很搭啊</d><d p="128.07000,1,25,16750848,1459832513,0,cda48583,1734407635">这个小学校的小体育馆……</d><d p="58.99100,1,25,16750848,1459832511,0,cda48583,1734405067">这学校的咖啡机看上去就很难喝……</d><d p="13.57500,1,25,16750848,1459832510,0,cda48583,1734403193">感谢字幕组</d><d p="969.89800,1,25,16777215,1459696303,0,ed20d488,1729849979">漂亮的螺旋走位</d><d p="624.24700,1,25,16777215,1458496934,0,5313e226,1697085305">2333333</d><d p="532.25000,1,25,16777215,1458496933,0,5313e226,1697084561">23333333</d><d p="1334.58000,1,25,9487136,1457852615,0,1d3f206c,1679457559">水母死不了吧</d><d p="1116.27000,1,25,9487136,1457852611,0,1d3f206c,1679445357">这一季yumi好喜欢翻跟斗啊</d><d p="1012.17000,1,25,9487136,1457852609,0,1d3f206c,1679439305">没有</d><d p="937.51300,1,25,9487136,1457852607,0,1d3f206c,1679435365">夫妻档</d><d p="576.94800,1,25,9487136,1457852600,0,1d3f206c,1679411681">这女的傻吧</d><d p="190.78200,1,25,9487136,1457852592,0,1d3f206c,1679389125">因缺思厅</d><d p="88.60600,1,25,9487136,1457852590,0,1d3f206c,1679383085">这集要控制Jim了，xana很吊啊</d><d p="67.10200,1,25,9487136,1457852589,0,1d3f206c,1679381101">跳OP的朋友你们好，我是萌萌的草绿君，我为什么看不见自己发的弹幕？</d><d p="54.37700,1,25,9487136,1457852589,0,1d3f206c,1679379749">跳OP的朋友你们好，我是萌萌的草绿君</d><d p="1.58800,1,25,9487136,1457852588,0,1d3f206c,1679377221">感谢字幕组</d><d p="619.75400,1,25,16777215,1457410339,0,8626d1b5,1666973635">2333333</d><d p="531.64800,1,25,16777215,1457410338,0,8626d1b5,1666971053">233333333</d><d p="300.99200,1,25,16777215,1457410334,0,8626d1b5,1666964683">odd不是左撇子咩</d><d p="267.62000,1,25,16777215,1457179698,0,197206d5,1660357365">吵架了</d><d p="88.76100,1,25,8700107,1457176023,0,197206d5,1660077197">好准</d><d p="18.76200,1,25,8700107,1457172410,0,197206d5,1660027845">感谢字幕组</d><d p="1146.18000,1,25,16777215,1456995922,0,d87f8ff3,1654388465">锤地表示愤怒</d><d p="621.67100,1,25,16777215,1456995917,0,d87f8ff3,1654381049">2333333狗叫好逼真</d><d p="530.44200,1,25,16777215,1456995915,0,d87f8ff3,1654378335">23333</d><d p="602.60900,1,25,16777215,1455688949,0,d4f03eec,1606121927">耳机反过来戴</d><d p="269.90900,1,25,16777215,1454512318,0,a198263e,1550833543">William日常挑起两对cp的吵架</d><d p="1125.99000,1,25,16777215,1454458092,0,e042e92c,1547670119">输出基本靠吼</d><d p="261.41300,1,25,16777215,1453900159,0,d2e80dd4,1525205813">弹幕呢</d><d p="1299.27000,1,25,16777215,1453561864,0,3f19ec44,1513155279">先处理水母它有可能重来吧  必须先把旁边清理了 你们可以思考一下啊</d><d p="495.25800,1,25,16777215,1453558249,0,3f19ec44,1513093189">wowwwwwwww 这是个毛线hardcore啊...这很明显更nu-disco好吗</d><d p="244.10000,1,25,16777215,1453558244,0,3f19ec44,1513074667">2333333</d><d p="221.45400,1,25,16777215,1453558243,0,3f19ec44,1513073097">自带天赋</d><d p="525.46900,1,25,16777215,1453036185,0,d2d0a982,1496788263">233333</d><d p="1373.11000,1,25,16777215,1452870664,0,b640ffb4,1490924121">考题不是知道了吗</d><d p="1153.92000,1,25,16777215,1452870661,0,b640ffb4,1490911743">为什么不跑</d><d p="723.19600,1,25,16777215,1452867054,0,b640ffb4,1490887881">这么高跳下去没事</d><d p="554.00500,1,25,16777215,1452867050,0,b640ffb4,1490876919">233333</d><d p="272.03600,1,25,16777215,1452867045,0,b640ffb4,1490857637">吵架了</d><d p="297.18000,1,25,16777215,1452867045,0,b640ffb4,1490860047">万能的JIM</d><d p="915.78900,1,25,16777215,1452495793,0,954369d6,1480927049">A你上一集明明超強...</d><d p="798.00400,1,25,16777215,1452495791,0,954369d6,1480919157">wt..</d><d p="633.95100,1,25,16777215,1452495784,0,954369d6,1480909689">W専拆人CP= =</d><d p="554.56900,1,25,16777215,1452495783,0,954369d6,1480907747">23333</d><d p="513.32000,1,25,16777215,1452495782,0,954369d6,1480906715">果然是童年 XANA竟然不直接殺了</d><d p="27.90900,1,25,16777215,1452395506,0,10e049b1,1478151313">感谢字幕组</d><d p="848.40000,1,25,14811775,1452265899,0,794dd9f7,1474826161">反正没有生命危险了</d><d p="271.47400,1,25,16777215,1452251242,0,d443a50c,1474155683">我擦，william一个情敌当两个用ww</d><d p="813.47900,1,25,16777215,1452049903,0,81dc689c,1469139175">A要进塔才能实体化</d><d p="739.70600,1,25,16777215,1451981062,0,8436e21f,1467439339">一层和二层间有个梯子吧</d><d p="270.67000,1,25,16777215,1451981053,0,8436e21f,1467425259">日常拌嘴</d><d p="35.35300,1,25,16777215,1451394571,0,7268385e,1450255173">有有</d><d p="41.38000,1,25,16777215,1451394570,0,7268385e,1450252783">酷毙</d><d p="621.57500,1,25,16777215,1451005769,0,976359fc,1439374555">odd我男神</d><d p="1211.16000,1,25,16777215,1450868824,0,34654a0e,1436436445">剧情需要</d><d p="1007.16000,1,25,16777215,1450354086,0,6b924a75,1423290625">我关了弹幕吗</d><d p="811.39100,1,25,16777215,1450339447,0,6b924a75,1422862917">就不能实体化她吗！</d><d p="708.30900,1,25,16777215,1450339445,0,6b924a75,1422860783">她被送过去那就实体化哇</d><d p="620.18100,1,25,16777215,1450339443,0,6b924a75,1422858453">hhhhhhhhhhhhhhhhh</d><d p="515.28400,1,25,16777215,1450339440,0,6b924a75,1422854793">蜜汁舞姿</d><d p="1356.76000,1,25,16777215,1448122325,0,f65e9b16,1361190059">是不杀，没有打要害</d><d p="1273.79000,1,25,16777215,1448122324,0,f65e9b16,1361185605">做事没一点主次，不会先救人</d><d p="1084.11000,1,25,16777215,1448118709,0,f65e9b16,1361139595">没蓝，而XANA是无限蓝</d><d p="332.12700,1,25,16777215,1448118698,0,f65e9b16,1361102621">折了两小时。。。</d><d p="1308.52000,1,25,52224,1447653742,0,e824dc9,1349367263">这么晚才砍水母，居然还没有弄完</d><d p="638.80400,1,25,16777215,1446390702,0,8655a08c,1319578847">木桩子。。。</d><d p="838.15400,1,25,16777215,1445998257,0,151c8cdb,1307955411">其实很多时候艾丽塔可以改变地形</d><d p="25.49500,1,25,16777215,1445998243,0,151c8cdb,1307941043">odd男神</d><d p="789.16600,1,25,16777215,1445933097,0,612d6a39,1306522703">woc</d><d p="560.91100,1,25,16777215,1445933093,0,612d6a39,1306517777">2333333</d><d p="1160.69000,1,25,16777215,1445688494,0,6dd9897c,1299688023">我去</d><d p="805.18200,1,25,16777215,1445688488,0,6dd9897c,1299666665">心疼Ulrich和odd</d><d p="797.10800,1,25,16777215,1445688487,0,6dd9897c,1299665463">what the fuc k</d><d p="783.79300,1,25,16777215,1445688487,0,6dd9897c,1299663761">屌爆了</d><d p="747.42300,1,25,16777215,1445688486,0,6dd9897c,1299661165">卧槽！</d><d p="668.04400,1,25,16777215,1445688484,0,6dd9897c,1299655535">Oh sir t</d><d p="493.41500,1,25,16777215,1445688481,0,6dd9897c,1299643407">WOW~够复古</d><d p="354.13000,1,25,16777215,1445684878,0,6dd9897c,1299634439">卧槽！</d><d p="32.18600,1,25,16777215,1445684872,0,6dd9897c,1299613433">有</d><d p="524.80900,1,25,16777215,1445670182,0,89c58fbb,1298737231">這慘叫</d><d p="275.03700,1,25,16777215,1445666577,0,89c58fbb,1298724439">吵架了</d><d p="39.69000,1,25,16777215,1445666573,0,89c58fbb,1298713707">前面從第一季看到現在的等等我</d><d p="740.78700,1,25,16777215,1445440297,0,a569668e,1293374367">电梯需要密码，但可以梯子爬下去</d><d p="36.32700,1,25,9599289,1445357535,0,5c26560e,1291787295">从第一季看到现在</d><d p="1237.67000,1,25,16777215,1445181075,0,8e4e0a0c,1288233105">你不能先砍水母吗……</d><d p="1090.04000,1,25,16777215,1445181072,0,8e4e0a0c,1288226601">稍微弄个墙壁挡一下都好啊</d><d p="437.03300,1,25,16777215,1445177450,0,8e4e0a0c,1288168641">果然挑最弱那个</d><d p="11.64500,1,25,16777215,1445080057,0,7ac64c46,1284452369">感谢+1</d><d p="272.82500,1,25,16777215,1444712471,0,af3a6289,1275929079">吵架了</d><d p="1334.53000,1,25,16777215,1444197741,0,c940ccdd,1263436033">←水母打不死</d><d p="602.70200,1,25,16777215,1444197728,0,c940ccdd,1263397829">aelita是头太大了嘛戴不上耳机……</d><d p="1352.32000,1,25,16777215,1444140611,0,fb56d7c5,1261542641">钵水母纲无敌得 杀不掉</d><d p="1368.09000,1,25,16777215,1444050583,0,b7c5d2b1,1257678223">久违的回溯</d><d p="1329.46000,1,25,16777215,1444050582,0,b7c5d2b1,1257675617">就不能搞死那只水母一次吗……</d><d p="1225.35000,1,25,16777215,1444050580,0,b7c5d2b1,1257667671">先砍再说，废话什么……</d><d p="279.83000,1,25,16777215,1444050564,0,b7c5d2b1,1257597319">终于吵架了</d><d p="1139.45000,1,25,16777215,1444039569,0,85d2dc47,1256824381">每次出来都要锤地..</d><d p="265.92400,1,25,16777215,1444035953,0,85d2dc47,1256769961">日常吃醋</d><d p="790.57800,1,25,6830715,1443798680,0,53af494a,1247833143">XANA变强好多...</d><d p="41.03100,1,25,16777215,1443784059,0,35160d71,1247043173">有经费了不是吗</d><d p="1165.72000,1,25,16777215,1443344746,0,6e20fce7,1235551259">为了剧情发展了 为了让我们看到女主高潮脸福利</d><d p="1131.80000,1,25,16777215,1443344745,0,6e20fce7,1235550059">卧槽  这个惨叫</d><d p="1127.13000,1,25,16777215,1442632274,0,80ef16a1,1217666645">第一次！</d><d p="825.79200,1,25,16777215,1442632272,0,80ef16a1,1217661747">目前还没见过Y打败Megatank</d><d p="738.93800,1,25,16777215,1442632267,0,80ef16a1,1217652001">XANA可以放电…</d><d p="385.25200,1,25,16777215,1442632261,0,80ef16a1,1217639965">第一次感染JIM</d><d p="581.27600,1,25,16777215,1442589066,0,fae45eae,1216978283">哗了狗了</d><d p="1081.82000,5,25,16777215,1441346558,0,cbf6b7a0,1187041621">a的能力比谁都吊，硬是坐等人来救</d><d p="1163.81000,1,25,16777215,1440784936,0,8e47af54,1164834613">wtf</d><d p="1149.70000,1,25,16777215,1440705846,0,d8f202d3,1160733821">每次读取一点，水母应该读取到一点东西了吧</d><d p="731.51300,1,25,16777215,1440702239,0,d8f202d3,1160729891">下控制层是要密码的。xana和jim好像都不知道密码啊</d><d p="340.83800,1,25,16777215,1440702232,0,d8f202d3,1160726233">一只纸鹤叠了2个小时~\(≧▽≦)/~</d><d p="1136.84000,1,25,16777215,1440590884,0,24c87f69,1155141825">为什么女主不跑</d><d p="270.89800,1,25,16777215,1440568963,0,4ee570aa,1153845345">小兩口吵架啦</d><d p="86.64100,1,25,16777215,1440568958,0,4ee570aa,1153828299">真准</d><d p="13.83200,1,25,16777215,1440568957,0,4ee570aa,1153822319">我是來看彈幕的⋯</d><d p="42.70200,1,25,16777215,1440568957,0,4ee570aa,1153824773">用愛點燃，希望之光！</d><d p="18.41800,1,25,16777215,1440504488,0,96a3938e,1151086553">第二季片头曲有点小变化</d><d p="373.51600,1,25,16777215,1440493509,0,44701c90,1150382409">可能是块头比较大吧</d><d p="324.01000,1,25,16777215,1440277520,0,f3e7a591,1140639867">灵魂画师！</d><d p="62.70400,1,25,16777215,1440151597,0,1e17dd3c,1134427249">弹幕好少。。。。。</d><d p="529.74700,1,25,16777215,1440065165,0,7f1f2e5b,1129901503">听得懂人话的狗</d><d p="317.68000,5,25,16776960,1439986101,0,24e57722,1126161987">藏笔帽里啊</d><d p="305.08500,5,25,16776960,1439986101,0,24e57722,1126161045">傻了吧</d><d p="27.83600,5,25,16776960,1439986096,0,24e57722,1126138717">又从第一季来的么</d><d p="6.11900,5,25,16776960,1439986095,0,24e57722,1126136999">感谢字幕组</d><d p="1198.81000,1,25,16777215,1439651468,0,fe223edf,1109739167">每次她都不跑在一旁观战我也是醉了</d><d p="512.02400,1,25,16777215,1439518235,0,5cdeee71,1102579731">迷醉的舞姿</d><d p="1077.48000,1,25,16777215,1439107459,0,b9d23561,1084652107">为什么为什么她这么弱！有技能不用！卧槽好心塞</d><d p="365.33200,1,25,16777215,1439107443,0,b9d23561,1084591677">又是Jim？</d><d p="1155.03000,1,25,16777215,1438395039,0,ac43e018,1051621693">还有很多次呢</d><d p="1143.77000,1,25,16777215,1438395039,0,ac43e018,1051620871">没有后视镜的摩托………</d><d p="306.43900,1,25,16777215,1437743391,0,87637b33,1024631757">这种题目两个小时。。。。。我也是醉了</d><d p="555.88200,1,25,16777215,1437581521,0,5a2d5d68,1017869087">hhhhhhh</d><d p="1147.91000,1,25,16777215,1437570592,0,24221fc9,1017381717">第几次了，poor aelita</d><d p="1140.57000,1,25,16777215,1437487822,0,ce350435,1013977293">总是第一个下场(ಥ_ಥ)</d><d p="873.63900,1,25,16777215,1437487817,0,ce350435,1013958095">我槽……这都行⊙▽⊙</d><d p="552.35200,1,25,16777215,1437487811,0,ce350435,1013933787">哈哈哈啊哈哈啊哈哈哈哈哈哈哈</d></i>